{"i":401705467,"homeTeam":{"name":"Brooklyn Nets","roster":{"playerOne":{"name":"Cameron Johnson","minutos":"34","rebotes":"6","asistencias":"4","puntos":"26"},"playerTwo":{"name":"Nic Claxton","minutos":"31","rebotes":"9","asistencias":"10","puntos":"8"},"playerThree":{"name":"Cam Thomas","minutos":"27","rebotes":"3","asistencias":"7","puntos":"23"},"playerFour":{"name":"D'Angelo Russell","minutos":"24","rebotes":"0","asistencias":"4","puntos":"7"},"playerFive":{"name":"Keon Johnson","minutos":"24","rebotes":"1","asistencias":"2","puntos":"12"},"playerSix":{"name":"Trendon Watford","minutos":"17","rebotes":"2","asistencias":"1","puntos":"5"},"playerSeven":{"name":"Jalen Wilson","minutos":"17","rebotes":"3","asistencias":"0","puntos":"9"},"playerEight":{"name":"Ziaire Williams","minutos":"25","rebotes":"1","asistencias":"1","puntos":"10"},"playerNine":{"name":"Day'Ron Sharpe","minutos":"18","rebotes":"5","asistencias":"0","puntos":"2"},"playerTen":{"name":"Tyson Etienne","minutos":"No jugo","rebotes":"No jugo","asistencias":"No jugo","puntos":"No jugo"},"playerEleven":{"name":"","minutos":"","rebotes":"","asistencias":"","puntos":""},"playerTwelve":{"name":"","minutos":"","rebotes":"","asistencias":"","puntos":""},"playerThirteen":{"name":"","minutos":"","rebotes":"","asistencias":"","puntos":""},"playerFourteen":{"name":"","minutos":"","rebotes":"","asistencias":"","puntos":""},"playerFifteen":{"name":"","minutos":"","rebotes":"","asistencias":"","puntos":""}}},"awayTeam":{"name":"Golden State Warriors","roster":{"playerOne":{"name":"Draymond Green","minutos":"34","rebotes":"7","asistencias":"10","puntos":"7"},"playerTwo":{"name":"Jimmy Butler III","minutos":"35","rebotes":"2","asistencias":"6","puntos":"25"},"playerThree":{"name":"Stephen Curry","minutos":"36","rebotes":"4","asistencias":"4","puntos":"40"},"playerFour":{"name":"Moses Moody","minutos":"29","rebotes":"5","asistencias":"2","puntos":"10"},"playerFive":{"name":"Brandin Podziemski","minutos":"1","rebotes":"0","asistencias":"0","puntos":"0"},"playerSix":{"name":"","minutos":"","rebotes":"","asistencias":"","puntos":""},"playerSeven":{"name":"","minutos":"","rebotes":"","asistencias":"","puntos":""},"playerEight":{"name":"","minutos":"","rebotes":"","asistencias":"","puntos":""},"playerNine":{"name":"","minutos":"","rebotes":"","asistencias":"","puntos":""},"playerTen":{"name":"Trayce Jackson-Davis","minutos":"No jugo","rebotes":"No jugo","asistencias":"No jugo","puntos":"No jugo"},"playerEleven":{"name":"","minutos":"","rebotes":"","asistencias":"","puntos":""},"playerTwelve":{"name":"","minutos":"","rebotes":"","asistencias":"","puntos":""},"playerThirteen":{"name":"","minutos":"","rebotes":"","asistencias":"","puntos":""},"playerFourteen":{"name":"","minutos":"","rebotes":"","asistencias":"","puntos":""},"playerFifteen":{"name":"","minutos":"","rebotes":"","asistencias":"","puntos":""}}}}