{"i":401705498,"homeTeam":{"name":"Toronto Raptors","roster":{"playerOne":{"name":"Scottie Barnes","minutos":"26","rebotes":"13","asistencias":"2","puntos":"14"},"playerTwo":{"name":"Orlando Robinson","minutos":"26","rebotes":"11","asistencias":"4","puntos":"13"},"playerThree":{"name":"RJ Barrett","minutos":"27","rebotes":"10","asistencias":"8","puntos":"14"},"playerFour":{"name":"Immanuel Quickley","minutos":"28","rebotes":"6","asistencias":"6","puntos":"15"},"playerFive":{"name":"Jared Rhoden","minutos":"26","rebotes":"3","asistencias":"0","puntos":"11"},"playerSix":{"name":"Jamison Battle","minutos":"12","rebotes":"3","asistencias":"0","puntos":"5"},"playerSeven":{"name":"Garrett Temple","minutos":"9","rebotes":"2","asistencias":"2","puntos":"0"},"playerEight":{"name":"Colin Castleton","minutos":"27","rebotes":"9","asistencias":"3","puntos":"7"},"playerNine":{"name":"A.J. Lawson","minutos":"33","rebotes":"12","asistencias":"0","puntos":"32"},"playerTen":{"name":"Jakob Poeltl","minutos":"No jugo","rebotes":"No jugo","asistencias":"No jugo","puntos":"No jugo"},"playerEleven":{"name":"","minutos":"","rebotes":"","asistencias":"","puntos":""},"playerTwelve":{"name":"","minutos":"","rebotes":"","asistencias":"","puntos":""},"playerThirteen":{"name":"","minutos":"","rebotes":"","asistencias":"","puntos":""},"playerFourteen":{"name":"","minutos":"","rebotes":"","asistencias":"","puntos":""},"playerFifteen":{"name":"","minutos":"","rebotes":"","asistencias":"","puntos":""}}},"awayTeam":{"name":"Washington Wizards","roster":{"playerOne":{"name":"Alex Sarr","minutos":"30","rebotes":"11","asistencias":"2","puntos":"16"},"playerTwo":{"name":"Kyshawn George","minutos":"28","rebotes":"3","asistencias":"3","puntos":"13"},"playerThree":{"name":"Jordan Poole","minutos":"23","rebotes":"3","asistencias":"1","puntos":"16"},"playerFour":{"name":"Bilal Coulibaly","minutos":"8","rebotes":"2","asistencias":"1","puntos":"4"},"playerFive":{"name":"Bub Carrington","minutos":"26","rebotes":"4","asistencias":"5","puntos":"5"},"playerSix":{"name":"","minutos":"","rebotes":"","asistencias":"","puntos":""},"playerSeven":{"name":"","minutos":"","rebotes":"","asistencias":"","puntos":""},"playerEight":{"name":"","minutos":"","rebotes":"","asistencias":"","puntos":""},"playerNine":{"name":"","minutos":"","rebotes":"","asistencias":"","puntos":""},"playerTen":{"name":"AJ Johnson","minutos":"23","rebotes":"3","asistencias":"3","puntos":"3"},"playerEleven":{"name":"","minutos":"","rebotes":"","asistencias":"","puntos":""},"playerTwelve":{"name":"","minutos":"","rebotes":"","asistencias":"","puntos":""},"playerThirteen":{"name":"","minutos":"","rebotes":"","asistencias":"","puntos":""},"playerFourteen":{"name":"","minutos":"","rebotes":"","asistencias":"","puntos":""},"playerFifteen":{"name":"","minutos":"","rebotes":"","asistencias":"","puntos":""}}}}