{"i":401705444,"homeTeam":{"name":"Memphis Grizzlies","roster":{"playerOne":{"name":"Jaren Jackson Jr.","minutos":"2","rebotes":"0","asistencias":"0","puntos":"0"},"playerTwo":{"name":"Jaylen Wells","minutos":"33","rebotes":"2","asistencias":"6","puntos":"12"},"playerThree":{"name":"Zach Edey","minutos":"27","rebotes":"5","asistencias":"2","puntos":"15"},"playerFour":{"name":"Luke Kennard","minutos":"35","rebotes":"3","asistencias":"7","puntos":"17"},"playerFive":{"name":"Desmond Bane","minutos":"36","rebotes":"10","asistencias":"10","puntos":"35"},"playerSix":{"name":"Brandon Clarke","minutos":"21","rebotes":"7","asistencias":"1","puntos":"11"},"playerSeven":{"name":"Lamar Stevens","minutos":"3","rebotes":"1","asistencias":"0","puntos":"0"},"playerEight":{"name":"GG Jackson","minutos":"28","rebotes":"7","asistencias":"3","puntos":"11"},"playerNine":{"name":"John Konchar","minutos":"15","rebotes":"1","asistencias":"0","puntos":"5"},"playerTen":{"name":"Cam Spencer","minutos":"No jugo","rebotes":"No jugo","asistencias":"No jugo","puntos":"No jugo"},"playerEleven":{"name":"","minutos":"","rebotes":"","asistencias":"","puntos":""},"playerTwelve":{"name":"","minutos":"","rebotes":"","asistencias":"","puntos":""},"playerThirteen":{"name":"","minutos":"","rebotes":"","asistencias":"","puntos":""},"playerFourteen":{"name":"","minutos":"","rebotes":"","asistencias":"","puntos":""},"playerFifteen":{"name":"","minutos":"","rebotes":"","asistencias":"","puntos":""}}},"awayTeam":{"name":"Atlanta Hawks","roster":{"playerOne":{"name":"Onyeka Okongwu","minutos":"32","rebotes":"12","asistencias":"2","puntos":"16"},"playerTwo":{"name":"Zaccharie Risacher","minutos":"32","rebotes":"1","asistencias":"0","puntos":"27"},"playerThree":{"name":"Dominick Barlow","minutos":"13","rebotes":"2","asistencias":"0","puntos":"6"},"playerFour":{"name":"Trae Young","minutos":"36","rebotes":"2","asistencias":"15","puntos":"12"},"playerFive":{"name":"Dyson Daniels","minutos":"33","rebotes":"3","asistencias":"7","puntos":"14"},"playerSix":{"name":"","minutos":"","rebotes":"","asistencias":"","puntos":""},"playerSeven":{"name":"","minutos":"","rebotes":"","asistencias":"","puntos":""},"playerEight":{"name":"","minutos":"","rebotes":"","asistencias":"","puntos":""},"playerNine":{"name":"","minutos":"","rebotes":"","asistencias":"","puntos":""},"playerTen":{"name":"Kevon Harris","minutos":"No jugo","rebotes":"No jugo","asistencias":"No jugo","puntos":"No jugo"},"playerEleven":{"name":"","minutos":"","rebotes":"","asistencias":"","puntos":""},"playerTwelve":{"name":"","minutos":"","rebotes":"","asistencias":"","puntos":""},"playerThirteen":{"name":"","minutos":"","rebotes":"","asistencias":"","puntos":""},"playerFourteen":{"name":"","minutos":"","rebotes":"","asistencias":"","puntos":""},"playerFifteen":{"name":"","minutos":"","rebotes":"","asistencias":"","puntos":""}}}}