{"i":401705538,"homeTeam":{"name":"Milwaukee Bucks","roster":{"playerOne":{"name":"Taurean Prince","minutos":"35","rebotes":"3","asistencias":"1","puntos":"14"},"playerTwo":{"name":"Giannis Antetokounmpo","minutos":"35","rebotes":"10","asistencias":"7","puntos":"34"},"playerThree":{"name":"Kyle Kuzma","minutos":"32","rebotes":"8","asistencias":"0","puntos":"8"},"playerFour":{"name":"Brook Lopez","minutos":"33","rebotes":"2","asistencias":"1","puntos":"10"},"playerFive":{"name":"Damian Lillard","minutos":"37","rebotes":"10","asistencias":"8","puntos":"25"},"playerSix":{"name":"Jericho Sims","minutos":"11","rebotes":"1","asistencias":"1","puntos":"0"},"playerSeven":{"name":"Gary Trent Jr.","minutos":"23","rebotes":"4","asistencias":"3","puntos":"13"},"playerEight":{"name":"Kevin Porter Jr.","minutos":"19","rebotes":"6","asistencias":"4","puntos":"16"},"playerNine":{"name":"AJ Green","minutos":"15","rebotes":"1","asistencias":"3","puntos":"6"},"playerTen":{"name":"Ryan Rollins","minutos":"No jugo","rebotes":"No jugo","asistencias":"No jugo","puntos":"No jugo"},"playerEleven":{"name":"","minutos":"","rebotes":"","asistencias":"","puntos":""},"playerTwelve":{"name":"","minutos":"","rebotes":"","asistencias":"","puntos":""},"playerThirteen":{"name":"","minutos":"","rebotes":"","asistencias":"","puntos":""},"playerFourteen":{"name":"","minutos":"","rebotes":"","asistencias":"","puntos":""},"playerFifteen":{"name":"","minutos":"","rebotes":"","asistencias":"","puntos":""}}},"awayTeam":{"name":"Indiana Pacers","roster":{"playerOne":{"name":"Pascal Siakam","minutos":"39","rebotes":"7","asistencias":"2","puntos":"26"},"playerTwo":{"name":"Aaron Nesmith","minutos":"36","rebotes":"4","asistencias":"2","puntos":"30"},"playerThree":{"name":"Myles Turner","minutos":"30","rebotes":"4","asistencias":"2","puntos":"14"},"playerFour":{"name":"Andrew Nembhard","minutos":"32","rebotes":"3","asistencias":"2","puntos":"7"},"playerFive":{"name":"Tyrese Haliburton","minutos":"37","rebotes":"6","asistencias":"15","puntos":"24"},"playerSix":{"name":"","minutos":"","rebotes":"","asistencias":"","puntos":""},"playerSeven":{"name":"","minutos":"","rebotes":"","asistencias":"","puntos":""},"playerEight":{"name":"","minutos":"","rebotes":"","asistencias":"","puntos":""},"playerNine":{"name":"","minutos":"","rebotes":"","asistencias":"","puntos":""},"playerTen":{"name":"Quenton Jackson","minutos":"No jugo","rebotes":"No jugo","asistencias":"No jugo","puntos":"No jugo"},"playerEleven":{"name":"","minutos":"","rebotes":"","asistencias":"","puntos":""},"playerTwelve":{"name":"","minutos":"","rebotes":"","asistencias":"","puntos":""},"playerThirteen":{"name":"","minutos":"","rebotes":"","asistencias":"","puntos":""},"playerFourteen":{"name":"","minutos":"","rebotes":"","asistencias":"","puntos":""},"playerFifteen":{"name":"","minutos":"","rebotes":"","asistencias":"","puntos":""}}}}